{
    "creators": [
        {
            "orcid": "0000-0001-8804-4216",
            "affiliation": "Research Institute for Nature and Forest (INBO)",
            "name": "Onkelinx, Thierry"
        }
    ],
    "contributors": [
        {
            "name": "Research Institute for Nature and Forest (INBO)",
            "type": "RightsHolder"
        }
    ],

    "access_rights": "open",
    "license": "GPL-3.0",

    "title": "territoria",
    "description": "Clustering Observations from Breeding Birds into Territoria",

    "related_identifiers": [
        {
            "scheme": "doi",
            "identifier": "10.1234/software.paper.5678",
            "relation": "isDocumentedBy",
            "resource_type": {
                "type": "publication",
                "subtype": "article"
            }
        }
    ],

    "keywords": ["R", "package", "bird", "territoria", "clustering"],

    "communities": [
        {"identifier": "inbo"}
    ],

    "upload_type": "software"
}
